odoo/addons/delivery_preference_glue_stock_picking_group/README.rst
odoo/addons/delivery_preference_glue_stock_picking_group/__init__.py
odoo/addons/delivery_preference_glue_stock_picking_group/__manifest__.py
odoo/addons/delivery_preference_glue_stock_picking_group/i18n/ca.po
odoo/addons/delivery_preference_glue_stock_picking_group/i18n/delivery_preference_glue_stock_picking_group.pot
odoo/addons/delivery_preference_glue_stock_picking_group/i18n/es_AR.po
odoo/addons/delivery_preference_glue_stock_picking_group/i18n/it.po
odoo/addons/delivery_preference_glue_stock_picking_group/i18n/pt_BR.po
odoo/addons/delivery_preference_glue_stock_picking_group/models/__init__.py
odoo/addons/delivery_preference_glue_stock_picking_group/models/stock_move.py
odoo/addons/delivery_preference_glue_stock_picking_group/readme/CONTRIBUTORS.rst
odoo/addons/delivery_preference_glue_stock_picking_group/readme/CREDITS.rst
odoo/addons/delivery_preference_glue_stock_picking_group/readme/DESCRIPTION.rst
odoo/addons/delivery_preference_glue_stock_picking_group/readme/ROADMAP.rst
odoo/addons/delivery_preference_glue_stock_picking_group/static/description/icon.png
odoo/addons/delivery_preference_glue_stock_picking_group/static/description/index.html
odoo/addons/delivery_preference_glue_stock_picking_group/tests/__init__.py
odoo/addons/delivery_preference_glue_stock_picking_group/tests/test_delivery_carrier_preference.py
odoo14_addon_delivery_preference_glue_stock_picking_group-14.0.1.0.1.dev7.dist-info/METADATA
odoo14_addon_delivery_preference_glue_stock_picking_group-14.0.1.0.1.dev7.dist-info/WHEEL
odoo14_addon_delivery_preference_glue_stock_picking_group-14.0.1.0.1.dev7.dist-info/top_level.txt
odoo14_addon_delivery_preference_glue_stock_picking_group-14.0.1.0.1.dev7.dist-info/RECORD
