Metadata-Version: 2.1
Name: odoo14-addon-delivery-preference-glue-stock-picking-group
Version: 14.0.1.0.1.dev7
Summary: Fix Delivery preferences module on grouping picking
Home-page: https://github.com/OCA/wms
Author: Camptocamp,Odoo Community Association (OCA)
Author-email: support@odoo-community.org
License: AGPL-3
Platform: UNKNOWN
Classifier: Programming Language :: Python
Classifier: Framework :: Odoo
Classifier: Framework :: Odoo :: 14.0
Classifier: License :: OSI Approved :: GNU Affero General Public License v3
Requires-Python: >=3.6
Requires-Dist: odoo14-addon-delivery-carrier-preference
Requires-Dist: odoo14-addon-stock-picking-group-by-partner-by-carrier
Requires-Dist: odoo <14.1dev,>=14.0a
